vibeUI/__init__.py
vibeUI/vibe.py
vibeui-1.0.0.dist-info/licenses/LICENSE
vibeui-1.0.0.dist-info/METADATA
vibeui-1.0.0.dist-info/WHEEL
vibeui-1.0.0.dist-info/top_level.txt
vibeui-1.0.0.dist-info/RECORD
