Metadata-Version: 2.4
Name: vibeUI
Version: 1.0.0
Summary: Beginner-friendly Python GUI library built on Tkinter
Author-email: Samarth Chugh <iforgot3360@gmail.com>
License: MIT
Project-URL: Homepage, https://github.com/Sam3360/vibeUI
Project-URL: Documentation, https://github.com/Sam3360/vibeUI
Classifier: Programming Language :: Python :: 3
Classifier: License :: OSI Approved :: MIT License
Classifier: Operating System :: OS Independent
Classifier: Topic :: Software Development :: User Interfaces
Requires-Python: >=3.7
License-File: LICENSE
Dynamic: license-file
